multimodal_autoencoders/__about__.py
multimodal_autoencoders/__init__.py
multimodal_autoencoders/joint_trainer.py
multimodal_autoencoders/base/__init__.py
multimodal_autoencoders/base/autoencoder.py
multimodal_autoencoders/base/base_dataset.py
multimodal_autoencoders/base/base_model.py
multimodal_autoencoders/data_loader/__init__.py
multimodal_autoencoders/data_loader/datasets.py
multimodal_autoencoders/model/__init__.py
multimodal_autoencoders/model/classifiers.py
multimodal_autoencoders/model/decoders.py
multimodal_autoencoders/model/encoders.py
multimodal_autoencoders/model/metric.py
multimodal_autoencoders-0.2.3.dist-info/METADATA
multimodal_autoencoders-0.2.3.dist-info/WHEEL
multimodal_autoencoders-0.2.3.dist-info/licenses/LICENSE
multimodal_autoencoders-0.2.3.dist-info/RECORD
