Metadata-Version: 2.1
Name: multimodal_autoencoders
Version: 0.2.3
Summary: Pytorch reimplementation of https://www.nature.com/articles/s41467-020-20249-2 for streamlined multidomain data integration and translation based on cross-modal autoencoders architectures
Project-URL: Documentation, https://github.com/Novartis/ChemBioMultimodalAutoencoders#readme
Project-URL: Issues, https://github.com/Novartis/ChemBioMultimodalAutoencoders/issues
Project-URL: Source, https://github.com/Novartis/ChemBioMultimodalAutoencoders
Author-email: "Thibault, Bechtler" <th.bechtler@gmail.com>, "Bartosz, Baranowski" <bartosz.baranowski@novartis.com>
License-Expression: MIT
License-File: LICENSE
Classifier: Development Status :: 4 - Beta
Classifier: Programming Language :: Python
Classifier: Programming Language :: Python :: 3.9
Classifier: Programming Language :: Python :: 3.10
Requires-Dist: dataclasses
Requires-Dist: numpy
Requires-Dist: scikit-learn
Requires-Dist: torch
